tnfr/__init__.py
tnfr/constants.py
tnfr/dynamics.py
tnfr/helpers.py
tnfr/main.py
tnfr/observers.py
tnfr/ontosim.py
tnfr/operators.py
tnfr_fer-2.0.0.dist-info/licenses/LICENSE.txt
tnfr_fer-2.0.0.dist-info/METADATA
tnfr_fer-2.0.0.dist-info/WHEEL
tnfr_fer-2.0.0.dist-info/entry_points.txt
tnfr_fer-2.0.0.dist-info/top_level.txt
tnfr_fer-2.0.0.dist-info/RECORD
