Metadata-Version: 2.4
Name: tnfr-fer
Version: 2.0.0
Summary: TNFR canónica: dinámica glífica modular sobre redes.
Author: Fer
License: MIT
Project-URL: Homepage, https://github.com/tuuser/tnfr
Project-URL: Issues, https://github.com/tuuser/tnfr/issues
Classifier: Programming Language :: Python :: 3
Classifier: Programming Language :: Python :: 3 :: Only
Classifier: Programming Language :: Python :: 3.9
Classifier: Programming Language :: Python :: 3.10
Classifier: Programming Language :: Python :: 3.11
Classifier: Programming Language :: Python :: 3.12
Classifier: License :: OSI Approved :: MIT License
Classifier: Operating System :: OS Independent
Requires-Python: >=3.9
License-File: LICENSE.txt
Requires-Dist: networkx>=2.6
Dynamic: license-file
